Metadata-Version: 2.1
Name: GCDetection
Version: 1.0.0
Summary: Project for using Cloud Vision API to quickly deployed the object detection application.
Home-page: https://github.com/Justin900429/GC-Detection
Author: Justin Ruan, Joyce Fang
Author-email: justin900429@gmail.com, objdoctor891213@gmail.com
License: MIT
Download-URL: https://github.com/Justin900429/GC-Detection/archive/0.9.0.tar.gz
Keywords: Google Cloud,Vision API,Object detection
Platform: UNKNOWN
Classifier: Programming Language :: Python :: 3
Classifier: License :: OSI Approved :: MIT License
Classifier: Operating System :: OS Independent
Requires-Python: >=3.6
